ragflow_async_sdk/__init__.py
ragflow_async_sdk/client.py
ragflow_async_sdk/http.py
ragflow_async_sdk/py.typed
ragflow_async_sdk/apis/__init__.py
ragflow_async_sdk/apis/agent.py
ragflow_async_sdk/apis/base.py
ragflow_async_sdk/apis/chat.py
ragflow_async_sdk/apis/chunk.py
ragflow_async_sdk/apis/dataset.py
ragflow_async_sdk/apis/document.py
ragflow_async_sdk/apis/file.py
ragflow_async_sdk/apis/mixins.py
ragflow_async_sdk/apis/session.py
ragflow_async_sdk/apis/system.py
ragflow_async_sdk/exceptions/__init__.py
ragflow_async_sdk/exceptions/api.py
ragflow_async_sdk/exceptions/base.py
ragflow_async_sdk/exceptions/config.py
ragflow_async_sdk/exceptions/http.py
ragflow_async_sdk/exceptions/validation.py
ragflow_async_sdk/models/__init__.py
ragflow_async_sdk/models/agent.py
ragflow_async_sdk/models/base.py
ragflow_async_sdk/models/chat.py
ragflow_async_sdk/models/chunk.py
ragflow_async_sdk/models/dataset.py
ragflow_async_sdk/models/document.py
ragflow_async_sdk/models/file.py
ragflow_async_sdk/models/session.py
ragflow_async_sdk/models/system.py
ragflow_async_sdk/models/task.py
ragflow_async_sdk/types/__init__.py
ragflow_async_sdk/types/common.py
ragflow_async_sdk/types/document.py
ragflow_async_sdk/types/file.py
ragflow_async_sdk/types/ingestion.py
ragflow_async_sdk/types/permission.py
ragflow_async_sdk/types/session.py
ragflow_async_sdk/utils/__init__.py
ragflow_async_sdk/utils/convertors.py
ragflow_async_sdk/utils/entity_helpers.py
ragflow_async_sdk/utils/files.py
ragflow_async_sdk/utils/normalizers.py
ragflow_async_sdk/utils/validators.py
ragflow_async_sdk-0.1.1.dist-info/METADATA
ragflow_async_sdk-0.1.1.dist-info/WHEEL
ragflow_async_sdk-0.1.1.dist-info/licenses/LICENSE
ragflow_async_sdk-0.1.1.dist-info/licenses/NOTICE
ragflow_async_sdk-0.1.1.dist-info/RECORD
