Metadata-Version: 2.4
Name: ragflow-async-sdk
Version: 0.1.1
Summary: Async Python SDK for RAGFlow
Author: OliverW
License: Apache-2.0
License-File: LICENSE
License-File: NOTICE
Requires-Python: >=3.10
Requires-Dist: httpx<0.30,>=0.28
Provides-Extra: dev
Requires-Dist: pytest; extra == 'dev'
Requires-Dist: pytest-asyncio; extra == 'dev'
